snowfall/__init__.py
snowfall/core/__init__.py
snowfall/core/snow_object.py
snowfall/data/__init__.py
snowfall/data/concat_data.py
snowfall/data/lambda_loader.py
snowfall/events/__init__.py
snowfall/events/execution.py
snowfall/generalization/__init__.py
snowfall/generalization/disturb_label.py
snowfall/generalization/early_stopping.py
snowfall/generalization/loss_regularizers.py
snowfall/losses/__init__.py
snowfall/losses/loss.py
snowfall/manager/__init__.py
snowfall/manager/execution_manager.py
snowfall/nn/__init__.py
snowfall/nn/circuit.py
snowfall/nn/module.py
snowfall/nn/network.py
snowfall/optimizers/__init__.py
snowfall/optimizers/adam.py
snowfall/optimizers/hessian_free.py
snowfall/optimizers/optimizer.py
snowfall_ml-0.1.0.dist-info/METADATA
snowfall_ml-0.1.0.dist-info/WHEEL
snowfall_ml-0.1.0.dist-info/top_level.txt
snowfall_ml-0.1.0.dist-info/RECORD
